<?xml version="1.0"?>

<iradio-cache version="1.0">
  <name>shoutcast</name>
  <station>
    <genre>Trance</genre>
    <name>Digitally Imported</name>
    <url>http://64.236.34.141:80/stream/1003</url>
  </station>
  <station>
    <genre>Metal</genre>
    <name>Sounds of Space Ghost</name>
    <url>http://localhost:8000</url>
  </station>
  <station>
    <genre>Broken</genre>
    <name>Broken Station Test</name>
    <url>http://this.hostname.does.not.exist</url>
  </station>
</iradio-cache>
    
  
